<?xml version='1.0' encoding='utf-8'?><m:page id='10b15785-d557-4e88-b0e7-b2bc03ed340a' xmlns='http://www.w3.org/1999/xhtml' title='Email log' class='mx-window-view' closeButton='48.EmailTemplate.EmailLog_View.cancelButton1' xmlns:m='http://schemas.mendix.com/forms/1.0'><m:parameters>["EmailLog"]</m:parameters><m:layouts><m:layout path='EmailTemplate/PopupLayout.layout.xml'></m:layout></m:layouts><m:arguments><m:argument parameterName='7807c235-bf52-4fa1-894a-d527a8f7df91'><div data-mendix-id='48.EmailTemplate.EmailLog_View.dataView1' data-mendix-type='mxui.widget.ReactWidgetWrapper' data-mendix-props='"widgetTree":[{"$widgetId":"48.EmailTemplate.EmailLog_View.dataView1","widget":"DataView","props":{"class":"mx-name-dataView1 form-vertical","object":{"$type":"AssociationObjectProperty","dataSourceId":"48.4","scope":"$EmailLog","editable":false},"emptyMessage":{"$type":"TextProperty","value":""},"body":[{"$widgetId":"48.EmailTemplate.EmailLog_View.table1","widget":"Table","props":{"class":"mx-name-table1","autoWidth":false,"columnWidths":["25%","75%"],"rows":[{"$widgetId":"48.EmailTemplate.EmailLog_View.table1$row0","widget":"TableRow","props":{"class":"","cells":[{"header":true,"class":"","content":[{"$widgetId":"48.EmailTemplate.EmailLog_View.label6","widget":"Label","props":{"class":"mx-name-label6","id":{"$type":"DerivedUniqueIdProperty","widgetId":"48.EmailTemplate.EmailLog_View.label6"},"caption":{"$type":"TextProperty","value":"Date"}}}]},{"class":"","content":[{"$widgetId":"48.EmailTemplate.EmailLog_View.datePicker1$formGroup","widget":"FormGroup","props":{"class":"mx-name-datePicker1 mx-datepicker","control":[{"$widgetId":"48.EmailTemplate.EmailLog_View.datePicker1","widget":"DatePicker","props":{"mode":"datetime","showCalendarButton":true,"inputValue":{"$type":"AttributeProperty","scope":"48.EmailTemplate.EmailLog_View.dataView1","path":"","entity":"EmailTemplate.EmailLog","attribute":"Created","onChange":{"type":"doNothing","argMap":{},"config":{},"disabledDuringExecution":false},"isEditable":{"expr":{"type":"literal","value":false},"args":{}},"validation":null,"formatting":{"dateFormat":{"type":"datetime"}}},"placeholder":{"$type":"TextProperty","value":""},"buttonLabel":{"$type":"TextProperty","value":"Show date picker"},"readOnlyStyle":"text","onEnter":null,"onLeave":null,"id":{"$type":"DerivedUniqueIdProperty","widgetId":"48.EmailTemplate.EmailLog_View.datePicker1"}}}],"labelFor":{"$type":"DerivedUniqueIdProperty","widgetId":"48.EmailTemplate.EmailLog_View.datePicker1"},"orientation":"vertical","hasError":{"$type":"ValidationProperty","inputWidgetId":"48.EmailTemplate.EmailLog_View.datePicker1"}}}]}]}},{"$widgetId":"48.EmailTemplate.EmailLog_View.table1$row1","widget":"TableRow","props":{"class":"","cells":[{"header":true,"class":"","content":[{"$widgetId":"48.EmailTemplate.EmailLog_View.label2","widget":"Label","props":{"class":"mx-name-label2","id":{"$type":"DerivedUniqueIdProperty","widgetId":"48.EmailTemplate.EmailLog_View.label2"},"caption":{"$type":"TextProperty","value":"Logtype"}}}]},{"class":"","content":[{"$widgetId":"48.EmailTemplate.EmailLog_View.dropDown1$formGroup","widget":"FormGroup","props":{"class":"mx-name-dropDown1 mx-dropdown","control":[{"$widgetId":"48.EmailTemplate.EmailLog_View.dropDown1","widget":"EnumSelect","props":{"value":{"$type":"AttributeProperty","scope":"48.EmailTemplate.EmailLog_View.dataView1","path":"","entity":"EmailTemplate.EmailLog","attribute":"Logtype","onChange":{"type":"doNothing","argMap":{},"config":{},"disabledDuringExecution":false},"isEditable":{"expr":{"type":"literal","value":false},"args":{}},"validation":null},"emptyOptionCaption":{"$type":"TextProperty","value":""},"readOnlyStyle":"text","onEnter":null,"onLeave":null,"id":{"$type":"DerivedUniqueIdProperty","widgetId":"48.EmailTemplate.EmailLog_View.dropDown1"}}}],"labelFor":{"$type":"DerivedUniqueIdProperty","widgetId":"48.EmailTemplate.EmailLog_View.dropDown1"},"orientation":"vertical","hasError":{"$type":"ValidationProperty","inputWidgetId":"48.EmailTemplate.EmailLog_View.dropDown1"}}}]}]}},{"$widgetId":"48.EmailTemplate.EmailLog_View.table1$row2","widget":"TableRow","props":{"class":"","cells":[{"header":true,"class":"","content":[{"$widgetId":"48.EmailTemplate.EmailLog_View.label3","widget":"Label","props":{"class":"mx-name-label3","id":{"$type":"DerivedUniqueIdProperty","widgetId":"48.EmailTemplate.EmailLog_View.label3"},"caption":{"$type":"TextProperty","value":"Message"}}}]},{"class":"","content":[{"$widgetId":"48.EmailTemplate.EmailLog_View.textArea2$formGroup","widget":"FormGroup","props":{"class":"mx-name-textArea2 mx-textarea","control":[{"$widgetId":"48.EmailTemplate.EmailLog_View.textArea2","widget":"TextArea","props":{"inputValue":{"$type":"AttributeProperty","scope":"48.EmailTemplate.EmailLog_View.dataView1","path":"","entity":"EmailTemplate.EmailLog","attribute":"Message","onChange":{"type":"doNothing","argMap":{},"config":{},"disabledDuringExecution":false},"isEditable":{"expr":{"type":"literal","value":false},"args":{}},"validation":null},"numberOfLines":5,"autoGrow":false,"placeholder":{"$type":"TextProperty","value":""},"readOnlyStyle":"text","onEnter":null,"onLeave":null,"submitWhileEditing":false,"submitDelay":300,"id":{"$type":"DerivedUniqueIdProperty","widgetId":"48.EmailTemplate.EmailLog_View.textArea2"}}}],"labelFor":{"$type":"DerivedUniqueIdProperty","widgetId":"48.EmailTemplate.EmailLog_View.textArea2"},"orientation":"vertical","hasError":{"$type":"ValidationProperty","inputWidgetId":"48.EmailTemplate.EmailLog_View.textArea2"}}}]}]}},{"$widgetId":"48.EmailTemplate.EmailLog_View.table1$row3","widget":"TableRow","props":{"class":"","cells":[{"header":true,"class":"","content":[{"$widgetId":"48.EmailTemplate.EmailLog_View.label4","widget":"Label","props":{"class":"mx-name-label4","id":{"$type":"DerivedUniqueIdProperty","widgetId":"48.EmailTemplate.EmailLog_View.label4"},"caption":{"$type":"TextProperty","value":"Error message"}}}]},{"class":"","content":[{"$widgetId":"48.EmailTemplate.EmailLog_View.textArea3$formGroup","widget":"FormGroup","props":{"class":"mx-name-textArea3 mx-textarea","control":[{"$widgetId":"48.EmailTemplate.EmailLog_View.textArea3","widget":"TextArea","props":{"inputValue":{"$type":"AttributeProperty","scope":"48.EmailTemplate.EmailLog_View.dataView1","path":"","entity":"EmailTemplate.EmailLog","attribute":"ErrorMessage","onChange":{"type":"doNothing","argMap":{},"config":{},"disabledDuringExecution":false},"isEditable":{"expr":{"type":"literal","value":false},"args":{}},"validation":null},"numberOfLines":5,"autoGrow":false,"placeholder":{"$type":"TextProperty","value":""},"readOnlyStyle":"text","onEnter":null,"onLeave":null,"submitWhileEditing":false,"submitDelay":300,"id":{"$type":"DerivedUniqueIdProperty","widgetId":"48.EmailTemplate.EmailLog_View.textArea3"}}}],"labelFor":{"$type":"DerivedUniqueIdProperty","widgetId":"48.EmailTemplate.EmailLog_View.textArea3"},"orientation":"vertical","hasError":{"$type":"ValidationProperty","inputWidgetId":"48.EmailTemplate.EmailLog_View.textArea3"}}}]}]}},{"$widgetId":"48.EmailTemplate.EmailLog_View.table1$row4","widget":"TableRow","props":{"class":"","cells":[{"header":true,"class":"","content":[{"$widgetId":"48.EmailTemplate.EmailLog_View.label5","widget":"Label","props":{"class":"mx-name-label5","id":{"$type":"DerivedUniqueIdProperty","widgetId":"48.EmailTemplate.EmailLog_View.label5"},"caption":{"$type":"TextProperty","value":"Triggered in MF"}}}]},{"class":"","content":[{"$widgetId":"48.EmailTemplate.EmailLog_View.textBox1$formGroup","widget":"FormGroup","props":{"class":"mx-name-textBox1 mx-textbox","control":[{"$widgetId":"48.EmailTemplate.EmailLog_View.textBox1","widget":"TextBox","props":{"inputValue":{"$type":"AttributeProperty","scope":"48.EmailTemplate.EmailLog_View.dataView1","path":"","entity":"EmailTemplate.EmailLog","attribute":"TriggeredInMF","onChange":{"type":"doNothing","argMap":{},"config":{},"disabledDuringExecution":false},"isEditable":{"expr":{"type":"literal","value":false},"args":{}},"validation":null,"formatting":{}},"isPassword":false,"placeholder":{"$type":"TextProperty","value":""},"mask":"","readOnlyStyle":"text","maxLength":200,"onEnter":null,"onLeave":null,"onEnterKeyPress":null,"autocomplete":"on","submitWhileEditing":false,"submitDelay":300,"id":{"$type":"DerivedUniqueIdProperty","widgetId":"48.EmailTemplate.EmailLog_View.textBox1"}}}],"labelFor":{"$type":"DerivedUniqueIdProperty","widgetId":"48.EmailTemplate.EmailLog_View.textBox1"},"orientation":"vertical","hasError":{"$type":"ValidationProperty","inputWidgetId":"48.EmailTemplate.EmailLog_View.textBox1"}}}]}]}},{"$widgetId":"48.EmailTemplate.EmailLog_View.table1$row5","widget":"TableRow","props":{"class":"","cells":[{"header":true,"class":"","content":[{"$widgetId":"48.EmailTemplate.EmailLog_View.label1","widget":"Label","props":{"class":"mx-name-label1","id":{"$type":"DerivedUniqueIdProperty","widgetId":"48.EmailTemplate.EmailLog_View.label1"},"caption":{"$type":"TextProperty","value":"Stacktrace"}}}]},{"class":"","content":[{"$widgetId":"48.EmailTemplate.EmailLog_View.textArea1$formGroup","widget":"FormGroup","props":{"class":"mx-name-textArea1 mx-textarea","control":[{"$widgetId":"48.EmailTemplate.EmailLog_View.textArea1","widget":"TextArea","props":{"inputValue":{"$type":"AttributeProperty","scope":"48.EmailTemplate.EmailLog_View.dataView1","path":"","entity":"EmailTemplate.EmailLog","attribute":"StackTrace","onChange":{"type":"doNothing","argMap":{},"config":{},"disabledDuringExecution":false},"isEditable":{"expr":{"type":"literal","value":false},"args":{}},"validation":null},"numberOfLines":5,"autoGrow":false,"placeholder":{"$type":"TextProperty","value":""},"readOnlyStyle":"text","onEnter":null,"onLeave":null,"submitWhileEditing":false,"submitDelay":300,"id":{"$type":"DerivedUniqueIdProperty","widgetId":"48.EmailTemplate.EmailLog_View.textArea1"}}}],"labelFor":{"$type":"DerivedUniqueIdProperty","widgetId":"48.EmailTemplate.EmailLog_View.textArea1"},"orientation":"vertical","hasError":{"$type":"ValidationProperty","inputWidgetId":"48.EmailTemplate.EmailLog_View.textArea1"}}}]}]}}]}}],"hideFooter":false,"footer":[{"$widgetId":"48.EmailTemplate.EmailLog_View.cancelButton1","widget":"ActionButton","props":{"buttonId":"48.EmailTemplate.EmailLog_View.cancelButton1","class":"mx-name-cancelButton1","renderType":"button","buttonClass":"btn-primary","caption":{"$type":"ExpressionProperty","expression":{"expr":{"type":"literal","value":"Close"},"args":{}}},"tooltip":{"$type":"TextProperty","value":""},"action":{"$type":"ActionProperty","action":{"type":"cancelChanges","argMap":{},"config":{"closePage":true},"disabledDuringExecution":true},"abortOnServerValidation":true}}}]}}],"listenTargets":[]'></div></m:argument></m:arguments></m:page>